tests/__init__.py
tests/test_word_information.py
wordInfo/__init__.py
wordInfo/word_information.py
word_information-0.1.5.dist-info/LICENSE
word_information-0.1.5.dist-info/METADATA
word_information-0.1.5.dist-info/WHEEL
word_information-0.1.5.dist-info/top_level.txt
word_information-0.1.5.dist-info/RECORD
