Metadata-Version: 2.1
Name: word-information
Version: 0.1.5
Summary: A fully functional dictionary module for Python to get the meanings, synonyms, antonyms and part-of-speech of a given word
Home-page: https://github.com/Bayo19/word-information
Author: Bayo Ade
Author-email: bayo.300@gmail.com
Keywords: word,dictionary,meaning,synonym,antonym,noun,verb,adjective,adverb,part-of-speech
Classifier: Intended Audience :: Developers
License-File: LICENSE
Requires-Dist: requests
Requires-Dist: bs4
